math_metods/__init__.py
math_metods/operacoes/__init__.py
math_metods/operacoes/basicas.py
math_metods/utils/__init__.py
math_metods/utils/complex.py
math_metods-0.0.3.dist-info/METADATA
math_metods-0.0.3.dist-info/WHEEL
math_metods-0.0.3.dist-info/top_level.txt
math_metods-0.0.3.dist-info/RECORD
