Metadata-Version: 2.1
Name: math-metods
Version: 0.0.3
Summary: Esta é a terceira tentativa de disponibilizar os methods
Author: Marcio
Author-email: marcioalexdias@gmail.com
Requires-Python: >=3.8
